lupin_logger/__init__.py
lupin_logger/constants.py
lupin_logger/logger.py
lupin_logger-0.2.0.dist-info/licenses/LICENSE
lupin_logger-0.2.0.dist-info/METADATA
lupin_logger-0.2.0.dist-info/WHEEL
lupin_logger-0.2.0.dist-info/top_level.txt
lupin_logger-0.2.0.dist-info/RECORD
