Metadata-Version: 2.4
Name: lupin_logger
Version: 0.2.0
Summary: LupinDental logger
Author-email: LupinDental <contact@lupindental.com>
Maintainer-email: LupinDental <contact@lupindental.com>
License: MIT
Project-URL: homepage, https://gitlab.com/lupindental/arsene/rd-utilities/lupin_logger
Classifier: Development Status :: 4 - Beta
Classifier: Topic :: System :: Logging
Requires-Python: >=3.11
License-File: LICENSE
Requires-Dist: colorama>=0.4.6
Dynamic: license-file
